[
  {
    "ID": "ZRT4PLF_01_D",
    "Name": "北庭站-1站台",
    "Situation": true,
    "Connect": true,
    "coordinate": {
      "x": 7451.5,
      "z": 3967.5
    },
    "lines": [
      {
        "ID": "ZRT4_01B_D",
        "Avaliable": true,
        "Overtaking": false,
        "getin": true,
        "getout": true,
        "NextOT": false
      }
    ],
    "Type": "Points",
    "Class": "PLF",
    "World": 0,
    "CreateTime": "20251225",
    "CreateBy": "639"
  },
  {
    "ID": "ZRT4PLF_01_U",
    "Name": "北庭站-2站台",
    "Situation": true,
    "Connect": true,
    "coordinate": {
      "x": 7467.5,
      "z": 3967.5
    },
    "lines": [
      {
        "ID": "ZRT4_01B_U",
        "Avaliable": true,
        "Overtaking": false,
        "getin": true,
        "getout": true,
        "NextOT": false
      }
    ],
    "Type": "Points",
    "Class": "PLF",
    "World": 0,
    "CreateTime": "20251225",
    "CreateBy": "639"
  },
  {
    "ID": "ZRT4STA_01",
    "Name": "北庭站",
    "coordinate": {
      "x": 7459.5,
      "z": 3967.5
    },
    "platforms": [
      {
        "ID": "ZRT4PLF_01_D"
      },
      {
        "ID": "ZRT4PLF_01_U"
      }
    ],
    "Type": "Points",
    "Class": "STA",
    "World": 0,
    "CreateTime": "20251225",
    "CreateBy": "639"
  },
  {
    "ID": "ZRT4PLF_02_D",
    "Name": "山滨站-1站台",
    "Situation": true,
    "Connect": true,
    "coordinate": {
      "x": 7077.5,
      "z": 4193.5
    },
    "lines": [
      {
        "ID": "ZRT4_01B_D",
        "Avaliable": true,
        "Overtaking": false,
        "getin": true,
        "getout": true,
        "NextOT": false
      }
    ],
    "Type": "Points",
    "Class": "PLF",
    "World": 0,
    "CreateTime": "20251225",
    "CreateBy": "639"
  },
  {
    "ID": "ZRT4PLF_02_U",
    "Name": "山滨站-2站台",
    "Situation": true,
    "Connect": true,
    "coordinate": {
      "x": 7077.5,
      "z": 4193.5
    },
    "lines": [
      {
        "ID": "ZRT4_01B_U",
        "Avaliable": true,
        "Overtaking": false,
        "getin": true,
        "getout": true,
        "NextOT": false
      }
    ],
    "Type": "Points",
    "Class": "PLF",
    "World": 0,
    "CreateTime": "20251225",
    "CreateBy": "639"
  },
  {
    "ID": "ZRT4STA_02",
    "Name": "山滨站",
    "coordinate": {
      "x": 7077.5,
      "z": 4193.5
    },
    "platforms": [
      {
        "ID": "ZRT4PLF_02_D"
      },
      {
        "ID": "ZRT4PLF_02_U"
      }
    ],
    "Type": "Points",
    "Class": "STA",
    "World": 0,
    "CreateTime": "20251225",
    "CreateBy": "639"
  },
  {
    "ID": "ZRT4PLF_03_D",
    "Name": "旧城站-1站台",
    "Situation": true,
    "Connect": true,
    "coordinate": {
      "x": 6793.5,
      "z": 4377.5
    },
    "lines": [
      {
        "ID": "ZRT4_01B_D",
        "Avaliable": true,
        "Overtaking": false,
        "getin": true,
        "getout": true,
        "NextOT": false
      }
    ],
    "Type": "Points",
    "Class": "PLF",
    "World": 0,
    "CreateTime": "20251225",
    "CreateBy": "639"
  },
  {
    "ID": "ZRT4PLF_03_U",
    "Name": "旧城站-2站台",
    "Situation": true,
    "Connect": true,
    "coordinate": {
      "x": 6793.5,
      "z": 4377.5
    },
    "lines": [
      {
        "ID": "ZRT4_01B_U",
        "Avaliable": true,
        "Overtaking": false,
        "getin": true,
        "getout": true,
        "NextOT": false
      }
    ],
    "Type": "Points",
    "Class": "PLF",
    "World": 0,
    "CreateTime": "20251225",
    "CreateBy": "639"
  },
  {
    "ID": "ZRT4STA_03",
    "Name": "旧城站",
    "coordinate": {
      "x": 6793.5,
      "z": 4377.5
    },
    "platforms": [
      {
        "ID": "ZRT4PLF_03_D"
      },
      {
        "ID": "ZRT4PLF_03_U"
      }
    ],
    "Type": "Points",
    "Class": "STA",
    "World": 0,
    "CreateTime": "20251225",
    "CreateBy": "639"
  },
  {
    "ID": "ZRT4PLF_04_D",
    "Name": "杉林站-1站台",
    "Situation": true,
    "Connect": true,
    "coordinate": {
      "x": 6521.5,
      "z": 4615.5
    },
    "lines": [
      {
        "ID": "ZRT4_01B_D",
        "Avaliable": true,
        "Overtaking": false,
        "getin": true,
        "getout": true,
        "NextOT": false
      }
    ],
    "Type": "Points",
    "Class": "PLF",
    "World": 0,
    "CreateTime": "20251225",
    "CreateBy": "639"
  },
  {
    "ID": "ZRT4PLF_04_U",
    "Name": "杉林站-2站台",
    "Situation": true,
    "Connect": true,
    "coordinate": {
      "x": 6521.5,
      "z": 4615.5
    },
    "lines": [
      {
        "ID": "ZRT4_01B_U",
        "Avaliable": true,
        "Overtaking": false,
        "getin": true,
        "getout": true,
        "NextOT": false
      }
    ],
    "Type": "Points",
    "Class": "PLF",
    "World": 0,
    "CreateTime": "20251225",
    "CreateBy": "639"
  },
  {
    "ID": "ZRT4STA_04",
    "Name": "杉林站",
    "coordinate": {
      "x": 6521.5,
      "z": 4615.5
    },
    "platforms": [
      {
        "ID": "ZRT4PLF_04_D"
      },
      {
        "ID": "ZRT4PLF_04_U"
      }
    ],
    "Type": "Points",
    "Class": "STA",
    "World": 0,
    "CreateTime": "20251225",
    "CreateBy": "639"
  },
  {
    "ID": "ZRT4PLF_05_D",
    "Name": "天门站-3站台",
    "Situation": true,
    "Connect": true,
    "coordinate": {
      "x": 5879.5,
      "z": 4615.5
    },
    "lines": [
      {
        "ID": "ZRT4_01B_D",
        "Avaliable": true,
        "Overtaking": false,
        "getin": true,
        "getout": true,
        "NextOT": false
      }
    ],
    "Type": "Points",
    "Class": "PLF",
    "World": 0,
    "CreateTime": "20251225",
    "CreateBy": "639"
  },
  {
    "ID": "ZRT4PLF_05_U",
    "Name": "天门站-4站台",
    "Situation": true,
    "Connect": true,
    "coordinate": {
      "x": 5879.5,
      "z": 4615.5
    },
    "lines": [
      {
        "ID": "ZRT4_01B_U",
        "Avaliable": true,
        "Overtaking": false,
        "getin": true,
        "getout": true,
        "NextOT": false
      }
    ],
    "Type": "Points",
    "Class": "PLF",
    "World": 0,
    "CreateTime": "20251225",
    "CreateBy": "639"
  },
  {
    "ID": "ZRT4STA_05",
    "Name": "天门站",
    "coordinate": {
      "x": 5879.5,
      "z": 4615.5
    },
    "platforms": [
      {
        "ID": "ZRT4PLF_05_D"
      },
      {
        "ID": "ZRT4PLF_05_U"
      }
    ],
    "Type": "Points",
    "Class": "STA",
    "World": 0,
    "CreateTime": "20251225",
    "CreateBy": "639"
  },
  {
    "ID": "ZRT4PLF_06_D",
    "Name": "湾北站-1站台",
    "Situation": true,
    "Connect": true,
    "coordinate": {
      "x": 5733.5,
      "z": 4615.5
    },
    "lines": [
      {
        "ID": "ZRT4_01B_D",
        "Avaliable": true,
        "Overtaking": false,
        "getin": true,
        "getout": true,
        "NextOT": false
      }
    ],
    "Type": "Points",
    "Class": "PLF",
    "World": 0,
    "CreateTime": "20251225",
    "CreateBy": "639"
  },
  {
    "ID": "ZRT4PLF_06_U",
    "Name": "湾北站-2站台",
    "Situation": true,
    "Connect": true,
    "coordinate": {
      "x": 5733.5,
      "z": 4615.5
    },
    "lines": [
      {
        "ID": "ZRT4_01B_U",
        "Avaliable": true,
        "Overtaking": false,
        "getin": true,
        "getout": true,
        "NextOT": false
      }
    ],
    "Type": "Points",
    "Class": "PLF",
    "World": 0,
    "CreateTime": "20251225",
    "CreateBy": "639"
  },
  {
    "ID": "ZRT4STA_06",
    "Name": "湾北站",
    "coordinate": {
      "x": 5733.5,
      "z": 4615.5
    },
    "platforms": [
      {
        "ID": "ZRT4PLF_06_D"
      },
      {
        "ID": "ZRT4PLF_06_U"
      }
    ],
    "Type": "Points",
    "Class": "STA",
    "World": 0,
    "CreateTime": "20251225",
    "CreateBy": "639"
  },
  {
    "ID": "ZRT4PLF_07_D",
    "Name": "沁洄川站-1站台",
    "Situation": true,
    "Connect": true,
    "coordinate": {
      "x": 5450.5,
      "z": 4615.5
    },
    "lines": [
      {
        "ID": "ZRT4_01B_D",
        "Avaliable": true,
        "Overtaking": false,
        "getin": true,
        "getout": true,
        "NextOT": false
      },
      {
        "ID": "ZRT4_01A_D",
        "Avaliable": true,
        "Overtaking": false,
        "getin": true,
        "getout": true,
        "NextOT": false
      }
    ],
    "Type": "Points",
    "Class": "PLF",
    "World": 0,
    "CreateTime": "20251225",
    "CreateBy": "639"
  },
  {
    "ID": "ZRT4PLF_07_U",
    "Name": "沁洄川站-2站台",
    "Situation": true,
    "Connect": true,
    "coordinate": {
      "x": 5450.5,
      "z": 4615.5
    },
    "lines": [
      {
        "ID": "ZRT4_01B_U",
        "Avaliable": true,
        "Overtaking": false,
        "getin": true,
        "getout": true,
        "NextOT": false
      },
      {
        "ID": "ZRT4_01A_U",
        "Avaliable": true,
        "Overtaking": false,
        "getin": true,
        "getout": true,
        "NextOT": false
      }
    ],
    "Type": "Points",
    "Class": "PLF",
    "World": 0,
    "CreateTime": "20251225",
    "CreateBy": "639"
  },
  {
    "ID": "ZRT4STA_07",
    "Name": "沁洄川站",
    "coordinate": {
      "x": 5450.5,
      "z": 4615.5
    },
    "platforms": [
      {
        "ID": "ZRT4PLF_07_D"
      },
      {
        "ID": "ZRT4PLF_07_U"
      }
    ],
    "Type": "Points",
    "Class": "STA",
    "World": 0,
    "CreateTime": "20251225",
    "CreateBy": "639"
  },
  {
    "ID": "ZRT4PLF_08_D",
    "Name": "北溯工站-3站台",
    "Situation": true,
    "Connect": true,
    "coordinate": {
      "x": 5296.5,
      "z": 4615.5
    },
    "lines": [
      {
        "ID": "ZRT4_01A_D",
        "Avaliable": true,
        "Overtaking": false,
        "getin": true,
        "getout": true,
        "NextOT": false
      }
    ],
    "Type": "Points",
    "Class": "PLF",
    "World": 0,
    "CreateTime": "20251225",
    "CreateBy": "639"
  },
  {
    "ID": "ZRT4PLF_08_U",
    "Name": "北溯工站-4站台",
    "Situation": true,
    "Connect": true,
    "coordinate": {
      "x": 5296.5,
      "z": 4615.5
    },
    "lines": [
      {
        "ID": "ZRT4_01A_U",
        "Avaliable": true,
        "Overtaking": false,
        "getin": true,
        "getout": true,
        "NextOT": false
      }
    ],
    "Type": "Points",
    "Class": "PLF",
    "World": 0,
    "CreateTime": "20251225",
    "CreateBy": "639"
  },
  {
    "ID": "ZRT4STA_08",
    "Name": "北溯工站",
    "coordinate": {
      "x": 5296.5,
      "z": 4615.5
    },
    "platforms": [
      {
        "ID": "ZRT4PLF_08_D"
      },
      {
        "ID": "ZRT4PLF_08_U"
      }
    ],
    "Type": "Points",
    "Class": "STA",
    "World": 0,
    "CreateTime": "20251225",
    "CreateBy": "639"
  },
  {
    "ID": "ZRT4PLF_09_D",
    "Name": "原央站-1站台",
    "Situation": true,
    "Connect": true,
    "coordinate": {
      "x": 5138.5,
      "z": 4615.5
    },
    "lines": [
      {
        "ID": "ZRT4_01A_D",
        "Avaliable": true,
        "Overtaking": false,
        "getin": true,
        "getout": true,
        "NextOT": false
      }
    ],
    "Type": "Points",
    "Class": "PLF",
    "World": 0,
    "CreateTime": "20251225",
    "CreateBy": "639"
  },
  {
    "ID": "ZRT4PLF_09_U",
    "Name": "原央站-2站台",
    "Situation": true,
    "Connect": true,
    "coordinate": {
      "x": 5138.5,
      "z": 4615.5
    },
    "lines": [
      {
        "ID": "ZRT4_01A_U",
        "Avaliable": true,
        "Overtaking": false,
        "getin": true,
        "getout": true,
        "NextOT": false
      }
    ],
    "Type": "Points",
    "Class": "PLF",
    "World": 0,
    "CreateTime": "20251225",
    "CreateBy": "639"
  },
  {
    "ID": "ZRT4STA_09",
    "Name": "原央站",
    "coordinate": {
      "x": 5138.5,
      "z": 4615.5
    },
    "platforms": [
      {
        "ID": "ZRT4PLF_09_D"
      },
      {
        "ID": "ZRT4PLF_09_U"
      }
    ],
    "Type": "Points",
    "Class": "STA",
    "World": 0,
    "CreateTime": "20251225",
    "CreateBy": "639"
  },
  {
    "ID": "ZRT4PLF_10_D",
    "Name": "白霖站-3站台",
    "Situation": true,
    "Connect": true,
    "coordinate": {
      "x": 4913.5,
      "z": 4615.5
    },
    "lines": [
      {
        "ID": "ZRT4_01A_D",
        "Avaliable": true,
        "Overtaking": false,
        "getin": true,
        "getout": true,
        "NextOT": false
      }
    ],
    "Type": "Points",
    "Class": "PLF",
    "World": 0,
    "CreateTime": "20251225",
    "CreateBy": "639"
  },
  {
    "ID": "ZRT4PLF_10_U",
    "Name": "白霖站-4站台",
    "Situation": true,
    "Connect": true,
    "coordinate": {
      "x": 4913.5,
      "z": 4615.5
    },
    "lines": [
      {
        "ID": "ZRT4_01A_U",
        "Avaliable": true,
        "Overtaking": false,
        "getin": true,
        "getout": true,
        "NextOT": false
      }
    ],
    "Type": "Points",
    "Class": "PLF",
    "World": 0,
    "CreateTime": "20251225",
    "CreateBy": "639"
  },
  {
    "ID": "ZRT4STA_10",
    "Name": "白霖站",
    "coordinate": {
      "x": 4913.5,
      "z": 4615.5
    },
    "platforms": [
      {
        "ID": "ZRT4PLF_10_D"
      },
      {
        "ID": "ZRT4PLF_10_U"
      }
    ],
    "Type": "Points",
    "Class": "STA",
    "World": 0,
    "CreateTime": "20251225",
    "CreateBy": "639"
  },
  {
    "ID": "ZRT4PLF_11_D",
    "Name": "三灯站-1站台",
    "Situation": true,
    "Connect": true,
    "coordinate": {
      "x": 4558.5,
      "z": 4818.5
    },
    "lines": [
      {
        "ID": "ZRT4_01A_D",
        "Avaliable": true,
        "Overtaking": false,
        "getin": true,
        "getout": true,
        "NextOT": false
      }
    ],
    "Type": "Points",
    "Class": "PLF",
    "World": 0,
    "CreateTime": "20251225",
    "CreateBy": "639"
  },
  {
    "ID": "ZRT4PLF_11_U",
    "Name": "三灯站-2站台",
    "Situation": true,
    "Connect": true,
    "coordinate": {
      "x": 4558.5,
      "z": 4818.5
    },
    "lines": [
      {
        "ID": "ZRT4_01A_U",
        "Avaliable": true,
        "Overtaking": false,
        "getin": true,
        "getout": true,
        "NextOT": false
      }
    ],
    "Type": "Points",
    "Class": "PLF",
    "World": 0,
    "CreateTime": "20251225",
    "CreateBy": "639"
  },
  {
    "ID": "ZRT4STA_11",
    "Name": "三灯站",
    "coordinate": {
      "x": 4558.5,
      "z": 4818.5
    },
    "platforms": [
      {
        "ID": "ZRT4PLF_11_D"
      },
      {
        "ID": "ZRT4PLF_11_U"
      }
    ],
    "Type": "Points",
    "Class": "STA",
    "World": 0,
    "CreateTime": "20251225",
    "CreateBy": "639"
  },
  {
    "ID": "ZRT4PLF_12_D",
    "Name": "四叶海岸站-1站台",
    "Situation": true,
    "Connect": true,
    "coordinate": {
      "x": 4558.5,
      "z": 5458.5
    },
    "lines": [
      {
        "ID": "ZRT4_01A_D",
        "Avaliable": true,
        "Overtaking": false,
        "getin": true,
        "getout": true,
        "NextOT": false
      }
    ],
    "Type": "Points",
    "Class": "PLF",
    "World": 0,
    "CreateTime": "20251225",
    "CreateBy": "639"
  },
  {
    "ID": "ZRT4PLF_12_U",
    "Name": "四叶海岸站-2站台",
    "Situation": true,
    "Connect": true,
    "coordinate": {
      "x": 4558.5,
      "z": 5458.5
    },
    "lines": [
      {
        "ID": "ZRT4_01A_U",
        "Avaliable": true,
        "Overtaking": false,
        "getin": true,
        "getout": true,
        "NextOT": false
      }
    ],
    "Type": "Points",
    "Class": "PLF",
    "World": 0,
    "CreateTime": "20251225",
    "CreateBy": "639"
  },
  {
    "ID": "ZRT4STA_12",
    "Name": "四叶海岸站",
    "coordinate": {
      "x": 4558.5,
      "z": 5458.5
    },
    "platforms": [
      {
        "ID": "ZRT4PLF_12_D"
      },
      {
        "ID": "ZRT4PLF_12_U"
      }
    ],
    "Type": "Points",
    "Class": "STA",
    "World": 0,
    "CreateTime": "20251225",
    "CreateBy": "639"
  },
  {
    "ID": "ZRT4PLF_13_D",
    "Name": "格兰南角站-1站台",
    "Situation": true,
    "Connect": true,
    "coordinate": {
      "x": 4558.5,
      "z": 5817.5
    },
    "lines": [
      {
        "ID": "ZRT4_01A_D",
        "Avaliable": true,
        "Overtaking": false,
        "getin": true,
        "getout": true,
        "NextOT": false
      }
    ],
    "Type": "Points",
    "Class": "PLF",
    "World": 0,
    "CreateTime": "20251225",
    "CreateBy": "639"
  },
  {
    "ID": "ZRT4PLF_13_U",
    "Name": "格兰南角站-2站台",
    "Situation": true,
    "Connect": true,
    "coordinate": {
      "x": 4558.5,
      "z": 5817.5
    },
    "lines": [
      {
        "ID": "ZRT4_01A_U",
        "Avaliable": true,
        "Overtaking": false,
        "getin": true,
        "getout": true,
        "NextOT": false
      }
    ],
    "Type": "Points",
    "Class": "PLF",
    "World": 0,
    "CreateTime": "20251225",
    "CreateBy": "639"
  },
  {
    "ID": "ZRT4STA_13",
    "Name": "格兰南角站",
    "coordinate": {
      "x": 4558.5,
      "z": 5817.5
    },
    "platforms": [
      {
        "ID": "ZRT4PLF_13_D"
      },
      {
        "ID": "ZRT4PLF_13_U"
      }
    ],
    "Type": "Points",
    "Class": "STA",
    "World": 0,
    "CreateTime": "20251225",
    "CreateBy": "639"
  },
  {
    "ID": "ZRT4PLF_14_D",
    "Name": "白令运河站-1站台",
    "Situation": true,
    "Connect": true,
    "coordinate": {
      "x": 4558.5,
      "z": 6042.5
    },
    "lines": [
      {
        "ID": "ZRT4_01A_D",
        "Avaliable": true,
        "Overtaking": false,
        "getin": true,
        "getout": true,
        "NextOT": false
      }
    ],
    "Type": "Points",
    "Class": "PLF",
    "World": 0,
    "CreateTime": "20251225",
    "CreateBy": "639"
  },
  {
    "ID": "ZRT4PLF_14_U",
    "Name": "白令运河站-2站台",
    "Situation": true,
    "Connect": true,
    "coordinate": {
      "x": 4558.5,
      "z": 6042.5
    },
    "lines": [
      {
        "ID": "ZRT4_01A_U",
        "Avaliable": true,
        "Overtaking": false,
        "getin": true,
        "getout": true,
        "NextOT": false
      }
    ],
    "Type": "Points",
    "Class": "PLF",
    "World": 0,
    "CreateTime": "20251225",
    "CreateBy": "639"
  },
  {
    "ID": "ZRT4STA_14",
    "Name": "白令运河站",
    "coordinate": {
      "x": 4558.5,
      "z": 6042.5
    },
    "platforms": [
      {
        "ID": "ZRT4PLF_14_D"
      },
      {
        "ID": "ZRT4PLF_14_U"
      }
    ],
    "Type": "Points",
    "Class": "STA",
    "World": 0,
    "CreateTime": "20251225",
    "CreateBy": "639"
  },
  {
    "ID": "ZRT4PLF_15_D",
    "Name": "快乐小镇站-1站台",
    "Situation": true,
    "Connect": true,
    "coordinate": {
      "x": 3718.5,
      "z": 6175.5
    },
    "lines": [
      {
        "ID": "ZRT4_01A_D",
        "Avaliable": true,
        "Overtaking": false,
        "getin": true,
        "getout": true,
        "NextOT": false
      }
    ],
    "Type": "Points",
    "Class": "PLF",
    "World": 0,
    "CreateTime": "20251225",
    "CreateBy": "639"
  },
  {
    "ID": "ZRT4PLF_15_U",
    "Name": "快乐小镇站-2站台",
    "Situation": true,
    "Connect": true,
    "coordinate": {
      "x": 3718.5,
      "z": 6175.5
    },
    "lines": [
      {
        "ID": "ZRT4_01A_U",
        "Avaliable": true,
        "Overtaking": false,
        "getin": true,
        "getout": true,
        "NextOT": false
      }
    ],
    "Type": "Points",
    "Class": "PLF",
    "World": 0,
    "CreateTime": "20251225",
    "CreateBy": "639"
  },
  {
    "ID": "ZRT4STA_15",
    "Name": "快乐小镇站",
    "coordinate": {
      "x": 3718.5,
      "z": 6175.5
    },
    "platforms": [
      {
        "ID": "ZRT4PLF_15_D"
      },
      {
        "ID": "ZRT4PLF_15_U"
      }
    ],
    "Type": "Points",
    "Class": "STA",
    "World": 0,
    "CreateTime": "20251225",
    "CreateBy": "639"
  },
  {
    "ID": "ZRT4PLF_16_D",
    "Name": "岭上神社站-1站台",
    "Situation": true,
    "Connect": true,
    "coordinate": {
      "x": 3425.5,
      "z": 6167.5
    },
    "lines": [
      {
        "ID": "ZRT4_01A_D",
        "Avaliable": true,
        "Overtaking": false,
        "getin": true,
        "getout": true,
        "NextOT": false
      },
      {
        "ID": "ZRT4_01C_D",
        "Avaliable": true,
        "Overtaking": false,
        "getin": true,
        "getout": true,
        "NextOT": false
      }
    ],
    "Type": "Points",
    "Class": "PLF",
    "World": 0,
    "CreateTime": "20251225",
    "CreateBy": "639"
  },
  {
    "ID": "ZRT4PLF_16_U",
    "Name": "岭上神社站-2站台",
    "Situation": true,
    "Connect": true,
    "coordinate": {
      "x": 3425.5,
      "z": 6183.5
    },
    "lines": [
      {
        "ID": "ZRT4_01A_U",
        "Avaliable": true,
        "Overtaking": false,
        "getin": true,
        "getout": true,
        "NextOT": false
      },
      {
        "ID": "ZRT4_01C_U",
        "Avaliable": true,
        "Overtaking": false,
        "getin": true,
        "getout": true,
        "NextOT": false
      }
    ],
    "Type": "Points",
    "Class": "PLF",
    "World": 0,
    "CreateTime": "20251225",
    "CreateBy": "639"
  },
  {
    "ID": "ZRT4STA_16",
    "Name": "岭上神社站",
    "coordinate": {
      "x": 3425.5,
      "z": 6175.5
    },
    "platforms": [
      {
        "ID": "ZRT4PLF_16_D"
      },
      {
        "ID": "ZRT4PLF_16_U"
      }
    ],
    "Type": "Points",
    "Class": "STA",
    "World": 0,
    "CreateTime": "20251225",
    "CreateBy": "639"
  },
  {
    "ID": "ZRT4PLF_17_D",
    "Name": "岭上西站-1站台",
    "Situation": true,
    "Connect": true,
    "coordinate": {
      "x": 3017.5,
      "z": 6405.5
    },
    "lines": [
      {
        "ID": "ZRT4_01C_D",
        "Avaliable": true,
        "Overtaking": false,
        "getin": true,
        "getout": true,
        "NextOT": false
      }
    ],
    "Type": "Points",
    "Class": "PLF",
    "World": 0,
    "CreateTime": "20251225",
    "CreateBy": "639"
  },
  {
    "ID": "ZRT4PLF_17_U",
    "Name": "岭上西站-2站台",
    "Situation": true,
    "Connect": true,
    "coordinate": {
      "x": 3017.5,
      "z": 6405.5
    },
    "lines": [
      {
        "ID": "ZRT4_01C_U",
        "Avaliable": true,
        "Overtaking": false,
        "getin": true,
        "getout": true,
        "NextOT": false
      }
    ],
    "Type": "Points",
    "Class": "PLF",
    "World": 0,
    "CreateTime": "20251225",
    "CreateBy": "639"
  },
  {
    "ID": "ZRT4STA_17",
    "Name": "岭上西站",
    "coordinate": {
      "x": 3017.5,
      "z": 6405.5
    },
    "platforms": [
      {
        "ID": "ZRT4PLF_17_D"
      },
      {
        "ID": "ZRT4PLF_17_U"
      }
    ],
    "Type": "Points",
    "Class": "STA",
    "World": 0,
    "CreateTime": "20251225",
    "CreateBy": "639"
  },
  {
    "ID": "ZRT4PLF_18_D",
    "Name": "幕沼站-1站台",
    "Situation": true,
    "Connect": true,
    "coordinate": {
      "x": 2885.5,
      "z": 6642.5
    },
    "lines": [
      {
        "ID": "ZRT4_01C_D",
        "Avaliable": true,
        "Overtaking": false,
        "getin": true,
        "getout": true,
        "NextOT": false
      }
    ],
    "Type": "Points",
    "Class": "PLF",
    "World": 0,
    "CreateTime": "20251225",
    "CreateBy": "639"
  },
  {
    "ID": "ZRT4PLF_18_U",
    "Name": "幕沼站-2站台",
    "Situation": true,
    "Connect": true,
    "coordinate": {
      "x": 2885.5,
      "z": 6642.5
    },
    "lines": [
      {
        "ID": "ZRT4_01C_U",
        "Avaliable": true,
        "Overtaking": false,
        "getin": true,
        "getout": true,
        "NextOT": false
      }
    ],
    "Type": "Points",
    "Class": "PLF",
    "World": 0,
    "CreateTime": "20251225",
    "CreateBy": "639"
  },
  {
    "ID": "ZRT4STA_18",
    "Name": "幕沼站",
    "coordinate": {
      "x": 2885.5,
      "z": 6642.5
    },
    "platforms": [
      {
        "ID": "ZRT4PLF_18_D"
      },
      {
        "ID": "ZRT4PLF_18_U"
      }
    ],
    "Type": "Points",
    "Class": "STA",
    "World": 0,
    "CreateTime": "20251225",
    "CreateBy": "639"
  },
  {
    "ID": "ZRT4PLF_19_D",
    "Name": "白给二号站-1站台",
    "Situation": true,
    "Connect": true,
    "coordinate": {
      "x": 2165.5,
      "z": 6642.5
    },
    "lines": [
      {
        "ID": "ZRT4_01C_D",
        "Avaliable": true,
        "Overtaking": false,
        "getin": true,
        "getout": true,
        "NextOT": false
      }
    ],
    "Type": "Points",
    "Class": "PLF",
    "World": 0,
    "CreateTime": "20251225",
    "CreateBy": "639"
  },
  {
    "ID": "ZRT4PLF_19_U",
    "Name": "白给二号站-2站台",
    "Situation": true,
    "Connect": true,
    "coordinate": {
      "x": 2165.5,
      "z": 6642.5
    },
    "lines": [
      {
        "ID": "ZRT4_01C_U",
        "Avaliable": true,
        "Overtaking": false,
        "getin": true,
        "getout": true,
        "NextOT": false
      }
    ],
    "Type": "Points",
    "Class": "PLF",
    "World": 0,
    "CreateTime": "20251225",
    "CreateBy": "639"
  },
  {
    "ID": "ZRT4STA_19",
    "Name": "白给二号站",
    "coordinate": {
      "x": 2165.5,
      "z": 6642.5
    },
    "platforms": [
      {
        "ID": "ZRT4PLF_19_D"
      },
      {
        "ID": "ZRT4PLF_19_U"
      }
    ],
    "Type": "Points",
    "Class": "STA",
    "World": 0,
    "CreateTime": "20251225",
    "CreateBy": "639"
  },
  {
    "ID": "ZRT4PLF_20_D",
    "Name": "星台站-1站台",
    "Situation": true,
    "Connect": true,
    "coordinate": {
      "x": 1923.5,
      "z": 6773.5
    },
    "lines": [
      {
        "ID": "ZRT4_01C_D",
        "Avaliable": true,
        "Overtaking": false,
        "getin": true,
        "getout": true,
        "NextOT": false
      }
    ],
    "Type": "Points",
    "Class": "PLF",
    "World": 0,
    "CreateTime": "20251225",
    "CreateBy": "639"
  },
  {
    "ID": "ZRT4PLF_20_U",
    "Name": "星台站-2站台",
    "Situation": true,
    "Connect": true,
    "coordinate": {
      "x": 1939.5,
      "z": 6773.5
    },
    "lines": [
      {
        "ID": "ZRT4_01C_U",
        "Avaliable": true,
        "Overtaking": false,
        "getin": true,
        "getout": true,
        "NextOT": false
      }
    ],
    "Type": "Points",
    "Class": "PLF",
    "World": 0,
    "CreateTime": "20251225",
    "CreateBy": "639"
  },
  {
    "ID": "ZRT4STA_20",
    "Name": "星台站",
    "coordinate": {
      "x": 1931.5,
      "z": 6773.5
    },
    "platforms": [
      {
        "ID": "ZRT4PLF_20_D"
      },
      {
        "ID": "ZRT4PLF_20_U"
      }
    ],
    "Type": "Points",
    "Class": "STA",
    "World": 0,
    "CreateTime": "20251225",
    "CreateBy": "639"
  },
  {
    "ID": "ZRT4PLF_21_D",
    "Name": "连东站-1站台",
    "Situation": true,
    "Connect": true,
    "coordinate": {
      "x": 1828.5,
      "z": 7057.5
    },
    "lines": [
      {
        "ID": "ZRT4_01C_D",
        "Avaliable": true,
        "Overtaking": false,
        "getin": true,
        "getout": true,
        "NextOT": false
      }
    ],
    "Type": "Points",
    "Class": "PLF",
    "World": 0,
    "CreateTime": "20251225",
    "CreateBy": "639",
    "ModifityTime": "20251225",
    "ModifityBy": "639"
  },
  {
    "ID": "ZRT4PLF_21_U",
    "Name": "连东站-2站台",
    "Situation": true,
    "Connect": true,
    "coordinate": {
      "x": 1828.5,
      "z": 7057.5
    },
    "lines": [
      {
        "ID": "ZRT4_01C_U",
        "Avaliable": true,
        "Overtaking": false,
        "getin": true,
        "getout": true,
        "NextOT": false
      }
    ],
    "Type": "Points",
    "Class": "PLF",
    "World": 0,
    "CreateTime": "20251225",
    "CreateBy": "639",
    "ModifityTime": "20251225",
    "ModifityBy": "639"
  },
  {
    "ID": "ZRT4STA_21",
    "Name": "连东站",
    "coordinate": {
      "x": 1828.5,
      "z": 7057.5
    },
    "platforms": [
      {
        "ID": "ZRT4PLF_21_D"
      },
      {
        "ID": "ZRT4PLF_21_U"
      }
    ],
    "Type": "Points",
    "Class": "STA",
    "World": 0,
    "CreateTime": "20251225",
    "CreateBy": "639",
    "ModifityTime": "20251225",
    "ModifityBy": "639"
  },
  {
    "ID": "ZRT4PLF_22_D",
    "Name": "连西站-1站台",
    "Situation": true,
    "Connect": true,
    "coordinate": {
      "x": 1563.5,
      "z": 7057.5
    },
    "lines": [
      {
        "ID": "ZRT4_01C_D",
        "Avaliable": true,
        "Overtaking": false,
        "getin": true,
        "getout": true,
        "NextOT": false
      }
    ],
    "Type": "Points",
    "Class": "PLF",
    "World": 0,
    "CreateTime": "20251225",
    "CreateBy": "639"
  },
  {
    "ID": "ZRT4PLF_22_U",
    "Name": "连西站-2站台",
    "Situation": true,
    "Connect": true,
    "coordinate": {
      "x": 1563.5,
      "z": 7057.5
    },
    "lines": [
      {
        "ID": "ZRT4_01C_U",
        "Avaliable": true,
        "Overtaking": false,
        "getin": true,
        "getout": true,
        "NextOT": false
      }
    ],
    "Type": "Points",
    "Class": "PLF",
    "World": 0,
    "CreateTime": "20251225",
    "CreateBy": "639"
  },
  {
    "ID": "ZRT4STA_22",
    "Name": "连西站",
    "coordinate": {
      "x": 1563.5,
      "z": 7057.5
    },
    "platforms": [
      {
        "ID": "ZRT4PLF_22_D"
      },
      {
        "ID": "ZRT4PLF_22_U"
      }
    ],
    "Type": "Points",
    "Class": "STA",
    "World": 0,
    "CreateTime": "20251225",
    "CreateBy": "639"
  },
  {
    "ID": "ZRT4PLF_23_D",
    "Name": "新桥站-1站台",
    "Situation": true,
    "Connect": true,
    "coordinate": {
      "x": 1263.5,
      "z": 6861.5
    },
    "lines": [
      {
        "ID": "ZRT4_01C_D",
        "Avaliable": true,
        "Overtaking": false,
        "getin": true,
        "getout": true,
        "NextOT": false
      }
    ],
    "Type": "Points",
    "Class": "PLF",
    "World": 0,
    "CreateTime": "20251225",
    "CreateBy": "639"
  },
  {
    "ID": "ZRT4PLF_23_U",
    "Name": "新桥站-2站台",
    "Situation": true,
    "Connect": true,
    "coordinate": {
      "x": 1263.5,
      "z": 6877.5
    },
    "lines": [
      {
        "ID": "ZRT4_01C_U",
        "Avaliable": true,
        "Overtaking": false,
        "getin": true,
        "getout": true,
        "NextOT": false
      }
    ],
    "Type": "Points",
    "Class": "PLF",
    "World": 0,
    "CreateTime": "20251225",
    "CreateBy": "639"
  },
  {
    "ID": "ZRT4STA_23",
    "Name": "新桥站",
    "coordinate": {
      "x": 1263.5,
      "z": 6869.5
    },
    "platforms": [
      {
        "ID": "ZRT4PLF_23_D"
      },
      {
        "ID": "ZRT4PLF_23_U"
      }
    ],
    "Type": "Points",
    "Class": "STA",
    "World": 0,
    "CreateTime": "20251225",
    "CreateBy": "639"
  }
]